autobolt/__init__.py
autobolt/__main__.py
autobolt-0.1.1.dist-info/LICENSE
autobolt-0.1.1.dist-info/METADATA
autobolt-0.1.1.dist-info/WHEEL
autobolt-0.1.1.dist-info/top_level.txt
autobolt-0.1.1.dist-info/RECORD
